lightrag/README.md
lightrag/__init__.py
lightrag/light_rag.py
lightrag/string_parser.py
lightrag/text_lightrag.txt
lightrag/tool_helper.py
lightrag-0.1.0.dist-info/LICENSE.md
lightrag-0.1.0.dist-info/METADATA
lightrag-0.1.0.dist-info/WHEEL
lightrag-0.1.0.dist-info/RECORD
