Metadata-Version: 2.1
Name: lightrag
Version: 0.1.0
Summary: 1000 lines of code is all you need. Be light and be lightening fast.
Author: Li Yin
Author-email: li.yin.gravity@gmail.com
Requires-Python: >=3.11,<3.12
Classifier: Programming Language :: Python :: 3
Classifier: Programming Language :: Python :: 3.11
Requires-Dist: backoff (>=2.2.1,<3.0.0)
Requires-Dist: faiss-cpu (>=1.8.0,<2.0.0)
Requires-Dist: groq (>=0.5.0,<0.6.0)
Requires-Dist: jinja2 (>=3.1.3,<4.0.0)
Requires-Dist: openai (>=1.12.0,<2.0.0)
Requires-Dist: pytest (>=8.1.1,<9.0.0)
Requires-Dist: python-dotenv (>=1.0.1,<2.0.0)
